MANIFEST.in
README.md
requirements.txt
setup.py
tasks/__init__.py
tasks_py.egg-info/PKG-INFO
tasks_py.egg-info/SOURCES.txt
tasks_py.egg-info/dependency_links.txt
tasks_py.egg-info/requires.txt
tasks_py.egg-info/top_level.txt