Metadata-Version: 1.0
Name: tasks-py
Version: 1.0.3
Summary: A simple and fast task queue for executing multiple tasks in parallel.
Home-page: https://github.com/vivekn/tasks
Author: Vivek Narayanan
Author-email: vivek@vivekn.com
License: BSD
Keywords: redis,multiprocessing,task queue
Platform: UNKNOWN
